pytonlib/__init__.py
pytonlib/client.py
pytonlib/tonlibjson.py
pytonlib/distlib/darwin/libtonlibjson.arm64.dylib
pytonlib/distlib/darwin/libtonlibjson.x86_64.dylib
pytonlib/distlib/freebsd/libtonlibjson.amd64.so
pytonlib/distlib/linux/libtonlibjson.aarch64.so
pytonlib/distlib/linux/libtonlibjson.x86_64.so
pytonlib/distlib/windows/tonlibjson.amd64.dll
pytonlib/utils/__init__.py
pytonlib/utils/address.py
pytonlib/utils/common.py
pytonlib/utils/tlb.py
pytonlib/utils/tokens.py
pytonlib/utils/wallet.py
pytonlib-0.0.68.dist-info/licenses/LICENSE
pytonlib-0.0.68.dist-info/METADATA
pytonlib-0.0.68.dist-info/WHEEL
pytonlib-0.0.68.dist-info/top_level.txt
pytonlib-0.0.68.dist-info/zip-safe
pytonlib-0.0.68.dist-info/RECORD
