Metadata-Version: 2.4
Name: pytonlib
Version: 0.0.68
Summary: Python API for TON (Telegram Open Network)
Home-page: https://github.com/toncenter/pytonlib
Author: K-Dimentional Tree
Author-email: kdimentionaltree@gmail.com
Classifier: Development Status :: 3 - Alpha
Classifier: Intended Audience :: Developers
Classifier: Programming Language :: Python :: 3.9
Classifier: Programming Language :: Python :: 3.10
Classifier: Programming Language :: Python :: 3.11
Classifier: Programming Language :: Python :: 3.12
Classifier: License :: Other/Proprietary License
Classifier: Topic :: Software Development :: Libraries
Requires-Python: >=3.7
License-File: LICENSE
Requires-Dist: crc16>=0.1.1
Requires-Dist: tvm_valuetypes==0.0.12
Requires-Dist: requests>=2.27.1
Dynamic: author
Dynamic: author-email
Dynamic: classifier
Dynamic: description
Dynamic: description-content-type
Dynamic: home-page
Dynamic: license-file
Dynamic: requires-dist
Dynamic: requires-python
Dynamic: summary
